gdmec21120421/__init__.py
gdmec21120421-0.1.0.dist-info/METADATA
gdmec21120421-0.1.0.dist-info/WHEEL
gdmec21120421-0.1.0.dist-info/entry_points.txt
gdmec21120421-0.1.0.dist-info/RECORD
